listofdicts/__init__.py
listofdicts/listofdicts.py
listofdicts-2.1.1.dist-info/licenses/LICENSE
listofdicts-2.1.1.dist-info/METADATA
listofdicts-2.1.1.dist-info/WHEEL
listofdicts-2.1.1.dist-info/top_level.txt
listofdicts-2.1.1.dist-info/RECORD
