Metadata-Version: 2.4
Name: listofdicts
Version: 2.1.1
Summary: A ListOfDicts class for managing a list of dictionaries with enhanced functionality.
Author-email: Stephen Hilton <stephen@familyhilton.com>
License-Expression: MIT
Keywords: list,dict,list of dict,listofdict,listofdicts
Requires-Python: >=3.8
License-File: LICENSE
Provides-Extra: dev
Requires-Dist: fupi; extra == "dev"
Provides-Extra: test
Requires-Dist: fupi; extra == "test"
Dynamic: license-file
